wallhaven_dl/__init__.py
wallhaven_dl/wallhaven_dl.py
wallhaven_dl-0.1.1.dist-info/LICENSE
wallhaven_dl-0.1.1.dist-info/METADATA
wallhaven_dl-0.1.1.dist-info/WHEEL
wallhaven_dl-0.1.1.dist-info/entry_points.txt
wallhaven_dl-0.1.1.dist-info/top_level.txt
wallhaven_dl-0.1.1.dist-info/RECORD
