Metadata-Version: 2.1
Name: wallhaven-dl
Version: 0.1.1
Summary: Download wallpaper from wallahaven.cc
Home-page: https://github.com/liuyaanng/wallhaven-dl
Author: GeekOcean
Author-email: liuyaanng@gmail.com
Classifier: Programming Language :: Python :: 3
Classifier: License :: OSI Approved :: MIT License
Classifier: Operating System :: OS Independent
License-File: LICENSE
Requires-Dist: PyYAML (==6.0)
Requires-Dist: requests (>=2.21.0)
Requires-Dist: rich (==12.6.0)
